torch_points3d/__init__.py
torch_points3d/applications/__init__.py
torch_points3d/applications/conf/kpconv/encoder_4.yaml
torch_points3d/applications/conf/kpconv/unet_4.yaml
torch_points3d/applications/conf/pointnet2/encoder_3_ms.yaml
torch_points3d/applications/conf/pointnet2/unet_3_ms.yaml
torch_points3d/applications/conf/pointnet2/unet_3_ss.yaml
torch_points3d/applications/conf/pointnet2/unet_4_ss.yaml
torch_points3d/applications/conf/rsconv/encoder_4.yaml
torch_points3d/applications/conf/rsconv/unet_4.yaml
torch_points3d/applications/conf/sparseconv3d/encoder_2.yaml
torch_points3d/applications/conf/sparseconv3d/encoder_4.yaml
torch_points3d/applications/conf/sparseconv3d/unet_2.yaml
torch_points3d/applications/conf/sparseconv3d/unet_4.yaml
torch_points3d/applications/kpconv.py
torch_points3d/applications/minkowski.py
torch_points3d/applications/modelfactory.py
torch_points3d/applications/models.py
torch_points3d/applications/pointnet2.py
torch_points3d/applications/pretrained_api.py
torch_points3d/applications/rsconv.py
torch_points3d/applications/sparseconv3d.py
torch_points3d/applications/utils.py
torch_points3d/core/__init__.py
torch_points3d/core/base_conv/__init__.py
torch_points3d/core/base_conv/base_conv.py
torch_points3d/core/base_conv/dense.py
torch_points3d/core/base_conv/message_passing.py
torch_points3d/core/base_conv/partial_dense.py
torch_points3d/core/common_modules/__init__.py
torch_points3d/core/common_modules/base_modules.py
torch_points3d/core/common_modules/dense_modules.py
torch_points3d/core/common_modules/gathering.py
torch_points3d/core/common_modules/spatial_transform.py
torch_points3d/core/data_transform/__init__.py
torch_points3d/core/data_transform/feature_augment.py
torch_points3d/core/data_transform/features.py
torch_points3d/core/data_transform/filters.py
torch_points3d/core/data_transform/grid_transform.py
torch_points3d/core/data_transform/inference_transforms.py
torch_points3d/core/data_transform/prebatchcollate.py
torch_points3d-1.2.0.dist-info/LICENSE.md
torch_points3d-1.2.0.dist-info/WHEEL
torch_points3d-1.2.0.dist-info/METADATA
torch_points3d-1.2.0.dist-info/RECORD
