Metadata-Version: 2.1
Name: torch-points3d
Version: 1.2.0
Summary: Point Cloud Deep Learning Extension Library for PyTorch
Author: Thomas Chaton
Author-email: thomas.chaton.ai@gmail.com
Requires-Python: >=3.6.1,<4.0.0
Classifier: Programming Language :: Python :: 3
Classifier: Programming Language :: Python :: 3.7
Classifier: Programming Language :: Python :: 3.8
Classifier: Programming Language :: Python :: 3.9
Requires-Dist: gdown (>=3.12.0,<4.0.0)
Requires-Dist: hydra-core (>=0.11.2,<0.12.0)
Requires-Dist: matplotlib (>=3.1,<4.0)
Requires-Dist: numba (>=0.49.0,<0.50.0)
Requires-Dist: numpy (>=1.18.2,<2.0.0)
Requires-Dist: open3d (==0.10.0.0)
Requires-Dist: plyfile (>=0.7.2,<0.8.0)
Requires-Dist: pytorch_metric_learning (>=0.9.87.dev0,<0.10.0)
Requires-Dist: scikit-image (>=0.16.2,<0.17.0)
Requires-Dist: tensorboard (>=2.1,<3.0)
Requires-Dist: torch (>=1.3.1,<2.0.0)
Requires-Dist: torch-cluster (>=1.5.6,<2.0.0)
Requires-Dist: torch-geometric (>=1.3.2,<2.0.0)
Requires-Dist: torch-points-kernels (>=0.6.6,<0.7.0)
Requires-Dist: torch-scatter (>=2.0.0,<3.0.0)
Requires-Dist: torch-sparse (>=0.6.0,<0.7.0)
Requires-Dist: torchnet (>=0.0.4,<0.0.5)
Requires-Dist: tqdm (>=4.40,<5.0)
Requires-Dist: wandb (>=0.8.18,<0.9.0)
Project-URL: Documentation, https://torch-points3d.readthedocs.io/en/latest/
